{"INDEX": 1035, "URL": "https://ksom.ac.in/", "OUTGOING_LINKS": [], "WORD_COUNT_MAP": {"career": 2, "current": 1, "open": 3, "posit": 1, "assist": 1, "professor": 4, "associ": 4, "pleas": 1, "click": 1, "detail": 1, "contact": 3, "address": 2, "kiit": 15, "school": 9, "manag": 18, "campu": 12, "bhubaneswar": 2, "odisha": 3, "india": 10, "question": 2, "infodesk": 3, "ksomacin": 2, "call": 2, "ksomacininstitut": 1, "genesi": 2, "histori": 2, "mission": 2, "vision": 2, "rank": 11, "recognit": 2, "intern": 8, "academ": 5, "tieup": 5, "infrastructur": 3, "world": 2, "class": 2, "librari": 3, "founder": 3, "pro": 2, "qualiti": 2, "assur": 2, "program": 9, "mba": 19, "full": 5, "time": 8, "ksom": 32, "advantag": 4, "structur": 6, "curriculum": 4, "summer": 2, "internship": 2, "elig": 4, "select": 3, "process": 6, "cours": 4, "fee": 6, "scholarship": 2, "appli": 22, "faq": 4, "super": 8, "busi": 5, "analyt": 5, "oper": 3, "suppli": 2, "chain": 2, "bba": 10, "phd": 10, "admiss": 6, "programm": 4, "award": 2, "faculti": 17, "research": 15, "pedagogi": 2, "regular": 2, "directori": 4, "visit": 3, "develop": 4, "public": 4, "parikalpana": 3, "journal": 3, "issn": 6, "advisor": 2, "project": 3, "book": 4, "confer": 4, "center": 2, "excel": 3, "coesal": 2, "recruit": 6, "corpor": 7, "placement": 4, "differenti": 2, "statist": 2, "student": 13, "profil": 2, "partnership": 4, "opportun": 2, "industri": 6, "event": 8, "konclav": 10, "famou": 3, "speaker": 2, "nation": 8, "market": 4, "financ": 4, "mdp": 4, "consult": 4, "calendar": 2, "complet": 2, "eventsproject": 2, "fund": 2, "seminar": 2, "talk": 3, "leadership": 2, "knowledg": 2, "entrepreneurship": 2, "life": 3, "news": 7, "blog": 5, "fight": 2, "covid": 2, "forthcom": 2, "activ": 5, "day": 2, "club": 4, "societi": 3, "virtual": 3, "tour": 3, "mentor": 4, "assess": 3, "centr": 2, "testimoni": 2, "alumni": 6, "speak": 8, "parent": 2, "kactiv": 2, "konfluenc": 2, "konfabul": 2, "konfid": 2, "konvers": 3, "kommuni": 2, "kare": 2, "kolosseumth": 2, "annual": 3, "mega": 2, "bschool": 6, "fest": 2, "prof": 2, "achyuta": 2, "samantafound": 1, "kissachyutasamantacom": 1, "institut": 6, "iim": 2, "iit": 1, "accredit": 3, "naac": 3, "grade": 2, "best": 4, "cat": 1, "mat": 1, "xat": 1, "cmat": 1, "score": 1, "kiite": 2, "one": 2, "largest": 1, "onlin": 1, "entranc": 1, "test": 1, "phase": 1, "result": 1, "studi": 1, "top": 2, "special": 1, "human": 1, "resourc": 1, "educ": 1, "transform": 1, "messag": 1, "websit": 1, "samanta": 1, "kiss": 1, "deem": 1, "univers": 1, "council": 1, "year": 1, "nirf": 2, "new": 1, "trend": 1, "offer": 1, "worldclass": 1, "unmatch": 1, "exposur": 1, "rich": 1, "environ": 1, "facultyksom": 1, "lifeth": 1, "abuzz": 1, "variou": 1, "interactionroundtheyear": 1, "workshop": 1, "person": 1, "placementvisit": 1, "sever": 1, "mnc": 1, "regularli": 1, "salari": 1, "risen": 1, "conduct": 2, "futur": 1, "embrac": 1, "sustain": 1, "divers": 1, "inclus": 1, "februari": 19, "host": 1, "icmr": 2, "stand": 1, "premier": 1, "platform": 1, "facilit": 1, "monthli": 1, "newslett": 1, "novemberdecemb": 1, "digit": 1, "commerc": 1, "publish": 1, "biswajit": 1, "design": 1, "exchequ": 1, "collabor": 1, "kraya": 1, "kuber": 1, "success": 1, "edit": 1, "pre": 1, "budget": 2, "discuss": 1, "theme": 1, "glimps": 1, "find": 1, "mail": 2, "intranet": 2, "latest": 1, "per": 3, "framework": 1, "mhrd": 1, "govern": 1, "week": 1, "hansa": 1, "survey": 1, "relat": 1, "kalinga": 2, "technolog": 1, "social": 1, "scienc": 1, "rural": 1, "quick": 1, "linksksom": 1, "practic": 1, "sitemap": 1, "icssr": 1, "counsel": 1, "cell": 1, "ksombbsr": 1, "glad": 1, "share": 3, "brajabal": 1, "love": 1, "reel": 1, "soumyadeepanand": 1, "tapsjyoti": 1, "proud": 1, "alumnu": 1, "akash": 1, "two": 1, "beauti": 1, "paint": 1, "wrap": 1, "batch": 1, "print": 1, "period": 1, "interna": 1, "happi": 1, "samar": 1, "pratap": 1, "nayak": 1, "congratul": 1, "ashim": 1, "saraswati": 1, "made": 1, "consider": 1, "contribut": 1, "shap": 1, "load": 1, "follow": 1, "instagram": 1, "enquir": 1, "archiv": 2, "month": 1, "decemb": 13, "novemb": 14, "octob": 14, "septemb": 14, "august": 14, "juli": 15, "june": 11, "april": 10, "march": 13, "januari": 14, "may": 8, "right": 1, "reserv": 1}}