{"INDEX": 186, "URL": "https://kp.kiit.ac.in/publication/", "OUTGOING_LINKS": [], "WORD_COUNT_MAP": {"skip": 1, "content": 1, "toggl": 2, "navigationfoundersap": 1, "portalmandatori": 1, "disclosuresgovern": 1, "bodynoticescareercontact": 1, "usadmissiontoggl": 1, "navigationhomeabout": 1, "usabout": 1, "usvis": 1, "missionspeci": 1, "featuresleadershipaffili": 1, "accreditationeoa": 1, "aict": 1, "affili": 1, "sctevt": 1, "accreditationacademicsacadem": 1, "calendartim": 1, "tablesyllabusstudi": 1, "materialscivil": 1, "engineeringcomput": 2, "scienc": 7, "engineeringelectr": 2, "engineeringelectron": 2, "telecommun": 2, "engineeringmechan": 2, "engineeringmetallurg": 2, "engineeringdepartmentscivil": 1, "engineeringappli": 1, "humanitiesplacementstudentsscholarshipsfinanci": 1, "assistancetutor": 1, "mentorfeedbackgrievancespeoplefacultystaffsresearchpublicationstud": 1, "projectsrnd": 1, "newsskillsskil": 1, "domaininternshipstud": 1, "clubaccolad": 1, "publicationadmint": 1, "research": 3, "publicationindex": 1, "googl": 1, "scholar": 1, "tripathi": 2, "panigrahi": 2, "studi": 6, "direct": 2, "torqu": 2, "control": 4, "phase": 1, "scim": 1, "two": 1, "threelevel": 1, "invert": 1, "use": 3, "stdtc": 1, "frdtc": 1, "scheme": 1, "engin": 6, "technolog": 3, "appli": 2, "mahala": 2, "nayak": 2, "mohanti": 2, "impact": 1, "enso": 1, "iod": 1, "tropic": 1, "cyclon": 1, "activ": 2, "bay": 1, "bengal": 1, "natur": 2, "hazard": 1, "mishra": 5, "sahu": 6, "modifi": 1, "octahedron": 1, "shape": 2, "antenna": 5, "parasit": 1, "load": 2, "plane": 1, "dual": 2, "band": 4, "notch": 4, "characterist": 2, "uwb": 4, "applic": 3, "intern": 2, "journal": 4, "microwav": 3, "computeraid": 1, "compact": 2, "circular": 2, "patch": 2, "wlan": 1, "optic": 2, "letter": 2, "inspir": 1, "tree": 1, "debata": 3, "plath": 1, "mirror": 1, "allse": 1, "eye": 1, "april": 1, "swb": 1, "confer": 3, "commun": 2, "signal": 1, "process": 2, "iccsp": 1, "ieee": 1, "rout": 1, "mukharje": 1, "roul": 1, "sekhar": 1, "dalai": 1, "may": 1, "valenc": 1, "electron": 1, "structur": 2, "hodop": 1, "mno": 1, "ultraviolet": 1, "photoemiss": 1, "spectroscopi": 1, "aip": 2, "proceed": 3, "vol": 2, "publish": 2, "llc": 1, "sahoo": 7, "mustakim": 1, "acid": 2, "alkali": 1, "chlorid": 1, "resist": 2, "concret": 4, "compos": 2, "lowcarbon": 1, "fli": 4, "ash": 4, "materi": 6, "civil": 1, "mahapatra": 3, "ann": 1, "model": 2, "strength": 2, "loss": 1, "long": 1, "term": 1, "sulphat": 1, "attack": 1, "today": 2, "element": 2, "post": 2, "coloni": 2, "cultur": 2, "hybrid": 4, "david": 2, "malouf": 2, "rememb": 2, "babylon": 2, "march": 1, "pore": 1, "character": 1, "prepar": 1, "carbon": 2, "iop": 2, "seri": 2, "controlbas": 1, "speed": 1, "threephas": 1, "squirrelcag": 1, "induct": 1, "motor": 1, "institut": 2, "india": 1, "simul": 1, "vsc": 1, "phailin": 1, "wrf": 1, "depart": 1, "kumar": 2, "jena": 2, "surekha": 1, "mechan": 1, "properti": 1, "cenospher": 1, "clamshel": 1, "filler": 1, "jute": 1, "epoxi": 1, "composit": 1, "advanc": 1, "manufactur": 1, "springer": 3, "singapor": 3, "dash": 1, "dualband": 1, "conic": 1, "dielectr": 1, "reson": 1, "improv": 1, "gain": 1, "iet": 1, "jaypuria": 2, "effect": 2, "arc": 1, "length": 1, "trim": 1, "adapt": 1, "pulsedmig": 1, "paramet": 1, "bead": 1, "profil": 1, "stainless": 1, "steel": 1, "synerg": 1, "power": 2, "sourc": 3, "constraint": 1, "journey": 1, "graphen": 1, "laboratori": 1, "life": 1, "recent": 2, "develop": 2, "sustain": 2, "infrastructur": 2, "priyadarshini": 1, "dutta": 1, "simultan": 1, "optim": 1, "bhatta": 1, "mohapatra": 1, "swain": 1, "panda": 1, "frequenc": 1, "divers": 1, "energi": 2, "integr": 1, "system": 1, "novel": 1, "harmoni": 1, "searchrandom": 1, "search": 1, "algorithm": 1, "design": 1, "fuzzyd": 1, "part": 1, "recoveri": 1, "util": 1, "environment": 1, "resourc": 1, "sap": 1, "portal": 1, "grievanc": 1, "cell": 1, "kiit": 7, "review": 1, "student": 1, "centr": 1, "antirag": 1, "quicklink": 1, "founder": 1, "kiss": 1, "foundat": 1, "art": 1, "give": 1, "kim": 1, "hospit": 1, "kiititi": 1, "address": 1, "polytechn": 1, "kolab": 1, "campu": 3, "bhubaneswar": 2, "email": 3, "protect": 2, "monday": 1, "saturday": 1, "slide": 1, "bar": 1, "area": 1, "founderdr": 1, "achyuta": 1, "samantacontact": 1, "info": 1, "kalinga": 1, "dental": 1, "kid": 2, "deem": 1, "univers": 1, "patia": 1, "phone": 1, "web": 1, "top": 1}}